kineticstoolkit_extensions/VERSION
kineticstoolkit_extensions/__init__.py
kineticstoolkit_extensions/anthropometry/__init__.py
kineticstoolkit_extensions/anthropometry/test_cgm.py
kineticstoolkit_extensions/anthropometry/test_com.py
kineticstoolkit_extensions/n3d/__init__.py
kineticstoolkit_extensions/n3d/test_n3d.py
kineticstoolkit_extensions/pushrimkinetics/__init__.py
kineticstoolkit_extensions/pushrimkinetics/test_pushrimkinetics.py
kineticstoolkit_extensions/video/__init__.py
kineticstoolkit_extensions-0.17.0.dist-info/licenses/LICENSE.txt
kineticstoolkit_extensions-0.17.0.dist-info/METADATA
kineticstoolkit_extensions-0.17.0.dist-info/WHEEL
kineticstoolkit_extensions-0.17.0.dist-info/top_level.txt
kineticstoolkit_extensions-0.17.0.dist-info/RECORD
