Metadata-Version: 2.4
Name: kineticstoolkit_extensions
Version: 0.17.0
Summary: Extensions and unstable development modules for Kinetics Toolkit.
Home-page: https://kineticstoolkit.uqam.ca
Author: Félix Chénier
Author-email: chenier.felix@uqam.ca
License: Apache
Project-URL: Documentation, https://kineticstoolkit.uqam.ca
Project-URL: Source, https://github.com/kineticstoolkit/kineticstoolkit_extensions
Project-URL: Tracker, https://github.com/kineticstoolkit/kineticstoolkit/issues
Classifier: Development Status :: 4 - Beta
Classifier: Intended Audience :: Science/Research
Classifier: License :: OSI Approved :: Apache Software License
Classifier: Natural Language :: English
Classifier: Operating System :: MacOS
Classifier: Operating System :: Microsoft :: Windows
Classifier: Operating System :: POSIX
Classifier: Programming Language :: Python :: 3
Requires-Python: >=3.10
License-File: LICENSE.txt
Requires-Dist: kineticstoolkit
Dynamic: author
Dynamic: author-email
Dynamic: classifier
Dynamic: description
Dynamic: description-content-type
Dynamic: home-page
Dynamic: license
Dynamic: license-file
Dynamic: project-url
Dynamic: requires-dist
Dynamic: requires-python
Dynamic: summary
